Metadata-Version: 2.1
Name: ovos-solver-alpacacpp-plugin
Version: 0.0.0a1
Summary: A question solver plugin for ovos
Home-page: https://github.com/OpenVoiceOS/ovos-solver-plugin-alpacacpp
Author: jarbasai
Author-email: jarbasai@mailfence.com
License: MIT
Keywords: ovos plugin utterance fallback query
Platform: UNKNOWN
Requires-Dist: ovos-solver-llamacpp-plugin
